{"objects":[{"id":"object-402492621185-0","velocityMax":100,"speed":100,"width":320,"height":80,"tags":{"obstacle":true,"stationary":true,"filled":true},"color":"#bf360c","spawnPointX":640,"spawnPointY":560,"subObjects":{}},{"id":"object-225058872040-0","velocityMax":100,"speed":100,"width":40,"height":200,"tags":{"obstacle":true,"goomba":true,"invisible":true},"color":"#cfd8dc","spawnPointX":640,"spawnPointY":360,"subObjects":{}},{"id":"object-909419753842-0","velocityMax":100,"speed":100,"width":360,"height":3200,"tags":{"obstacle":true,"stationary":true,"filled":true},"color":"#3e2723","spawnPointX":0,"spawnPointY":640,"subObjects":{}},{"id":"object-993793782499-0","velocityMax":100,"speed":100,"width":240,"height":40,"tags":{"obstacle":true,"filled":true},"color":"#5d4037","spawnPointX":680,"spawnPointY":640,"subObjects":{}},{"id":"object-471333105476-0","velocityMax":100,"speed":100,"width":440,"height":80,"tags":{"obstacle":true,"filled":true},"color":"#5d4037","spawnPointX":360,"spawnPointY":680,"subObjects":{}},{"id":"object-275853831600-0","velocityMax":100,"speed":100,"width":2680,"height":40,"tags":{"obstacle":true,"stationary":true,"talker":true,"talkOnHeroInteract":true,"oneTimeTalker":true,"filled":true},"color":"#194d33","spawnPointX":360,"spawnPointY":3160,"heroDialogue":["Oh no, Baby Bird!  You fell down! It's okay, just eat seeds to build up your strength and get back home."],"subObjects":{}},{"id":"object-1224415258979-0","velocityMax":100,"speed":100,"width":320,"height":40,"tags":{"obstacle":true,"filled":true},"color":"#3e2723","spawnPointX":360,"spawnPointY":3000,"subObjects":{}},{"id":"object-1419090227356-0","velocityMax":100,"speed":100,"width":120,"height":40,"tags":{"obstacle":true,"filled":true},"color":"#3e2723","spawnPointX":360,"spawnPointY":2880,"subObjects":{}},{"id":"object-879092828628-0","velocityMax":100,"speed":100,"width":40,"height":520,"tags":{"obstacle":true,"filled":true},"color":"#3e2723","spawnPointX":1200,"spawnPointY":3120,"subObjects":{}}],"world":{"id":"world-1585960200683","lockCamera":{"x":0,"y":0,"width":3200,"height":3200,"centerX":1600,"centerY":1600,"limitX":1600,"limitY":1600},"gameBoundaries":null,"procedural":{},"worldSpawnPointX":760,"worldSpawnPointY":480,"tags":{"calculatePathCollisions":false,"noCamping":true,"targetOnSight":true,"isAsymmetric":false,"shouldRestoreHero":false,"paused":false},"syncHero":false},"grid":{"width":80,"height":80,"nodeSize":40,"startX":0,"startY":0},"tags":{},"customInputBehavior":[],"defaultHero":{"id":"hero-1046714244015","actionButtonBehavior":"none","arrowKeysBehavior":"flatDiagonal","jumpVelocity":-480,"velocityMax":400,"speed":150,"width":40,"height":40,"flags":{"showDialogue":false,"showScore":false,"showLives":false,"paused":false},"tags":{"hero":true,"isPlayer":true,"filled":true},"zoomMultiplier":1.875,"color":"#e57373","lives":10,"spawnPointX":760},"id":"birdie"}
