{"id":"hello","world":{"id":"world-698059451746","lockCamera":null,"gameBoundaries":null,"proceduralBoundaries":null,"worldSpawnPointX":null,"worldSpawnPointY":null,"tags":{"calculatePathCollisions":true,"noCamping":false,"targetOnSight":false,"isAsymmetric":false,"shouldRestoreHero":false,"storeEntireGameState":false,"overrideCustomGameCode":false,"shadows":false,"ambientLight":0.2},"gravityVelocityY":1000,"gravityVelocityX":1000,"sequences":{}},"objects":[],"grid":{"width":80,"height":80,"nodeSize":32,"startX":0,"startY":0,"nodeData":{}}}